mlp_gpt_jax/__init__.py
mlp_gpt_jax/mlp_gpt_jax.py
mlp_gpt_jax/utils.py
mlp_gpt_jax-0.0.20.dist-info/LICENSE
mlp_gpt_jax-0.0.20.dist-info/METADATA
mlp_gpt_jax-0.0.20.dist-info/WHEEL
mlp_gpt_jax-0.0.20.dist-info/top_level.txt
mlp_gpt_jax-0.0.20.dist-info/RECORD
